{
  "siteType": "turkey",
  "basicProperties": {
    "siteName": "土耳其站",
    "shareGlobalAccount": 2,
    "walletType": 2,
    "storageType": 1,
    "siteDomainType": 2,
    "siteDomain": "www.kucoin.tr",
    "siteRegion": null,
    "brandType": 2,
    "logoType": 2
  },
  "extProperties": [],
  "functions": [
    {
      "code": "api_broker",
      "value": false
    },
    {
      "code": "fast_trade",
      "value": false
    },
    {
      "code": "spot_growth",
      "value": true
    },
    {
      "code": "3rd_party",
      "value": false
    },
    {
      "code": "convert",
      "value": true
    },
    {
      "code": "seo",
      "value": true
    },
    {
      "code": "trading_bot",
      "value": false
    },
    {
      "code": "financial_system",
      "value": true
    },
    {
      "code": "kyc",
      "value": true
    },
    {
      "code": "home_page",
      "value": true
    },
    {
      "code": "affiliate",
      "value": false
    },
    {
      "code": "nd_broker",
      "value": false
    },
    {
      "code": "spot",
      "value": true
    },
    {
      "code": "option",
      "value": false
    },
    {
      "code": "reconciliation_system",
      "value": true
    },
    {
      "code": "etf",
      "value": false
    },
    {
      "code": "payment",
      "value": true
    },
    {
      "code": "kucard",
      "value": false
    },
    {
      "code": "platform_growth",
      "value": true
    },
    {
      "code": "tax_platform",
      "value": true
    },
    {
      "code": "copy_trading",
      "value": false
    },
    {
      "code": "loan",
      "value": false
    },
    {
      "code": "data_center",
      "value": true
    },
    {
      "code": "invite_rebate",
      "value": false
    },
    {
      "code": "api",
      "value": true
    },
    {
      "code": "message_center",
      "value": true
    },
    {
      "code": "margin",
      "value": false
    },
    {
      "code": "web3_wallet",
      "value": false
    },
    {
      "code": "customer_service_system",
      "value": true
    },
    {
      "code": "financing",
      "value": false
    },
    {
      "code": "personal_center",
      "value": true
    },
    {
      "code": "rebate_business",
      "value": false
    },
    {
      "code": "p2p",
      "value": false
    },
    {
      "code": "search",
      "value": true
    },
    {
      "code": "fiat_deposit",
      "value": true
    },
    {
      "code": "futures",
      "value": false
    },
    {
      "code": "risk_control_system",
      "value": true
    },
    {
      "code": "currency",
      "value": true
    },
    {
      "code": "k_line",
      "value": true
    },
    {
      "code": "kucoin_pay",
      "value": false
    },
    {
      "code": "basic_bench",
      "value": true
    },
    {
      "code": "express",
      "value": true
    },
    {
      "code": "ucenter",
      "value": true
    },
    {
      "code": "activity_bench",
      "value": true
    },
    {
      "code": "kyb",
      "value": true
    },
    {
      "code": "compliance_exhibition_platform",
      "value": true
    }
  ],
  "bizConfigs": [
    {
      "code": "contract_liquidity",
      "value": ""
    },
    {
      "code": "shield_currency",
      "value": ""
    },
    {
      "code": "spot_liquidity",
      "value": "shared_liquidity"
    },
    {
      "code": "is_allowed_multilevel_rebate",
      "value": ""
    },
    {
      "code": "quote_currency",
      "value": "USDT"
    },
    {
      "code": "rebate_range",
      "value": ""
    }
  ]
}